scadnlp/__init__.py
scadnlp/main.py
scadnlp/prompts.py
scadnlp-2025.12.20175356.dist-info/METADATA
scadnlp-2025.12.20175356.dist-info/WHEEL
scadnlp-2025.12.20175356.dist-info/top_level.txt
scadnlp-2025.12.20175356.dist-info/RECORD
