Metadata-Version: 2.4
Name: scadnlp
Version: 2025.12.20175356
Summary: **The Package** is a specialized tool designed to bridge the gap between casual text descriptions and precise, structured 3D modeling instructions—specifically for **OpenSCAD**, the powerful yet text-
Author-email: scadnlp <hi@eugene.plus>
License: MIT
Project-URL: Homepage, https://github.com/chigwell/scadnlp
Requires-Python: >=3.9
Requires-Dist: langchain-llm7>=0.0.0
Requires-Dist: llmatch-messages>=0.0.0
Requires-Dist: langchain-core>=0.3.0
